FE_3DGQA/__init__.py
FE_3DGQA/app.py
FE_3DGQA/model.py
FE_3DGQA/data/__init__.py
FE_3DGQA/data/scannet/__init__.py
FE_3DGQA/data/scannet/batch_load_scannet_data.py
FE_3DGQA/data/scannet/load_scannet_data.py
FE_3DGQA/data/scannet/model_util_scannet.py
FE_3DGQA/data/scannet/scannet_utils.py
FE_3DGQA/data/scannet/visualize.py
FE_3DGQA/data/scannet/meta_data/__init__.py
FE_3DGQA/lib/__init__.py
FE_3DGQA/lib/ap_helper/__init__.py
FE_3DGQA/lib/ap_helper/ap_helper_fcos.py
FE_3DGQA/lib/ap_helper/ap_helper_votenet.py
FE_3DGQA/lib/configs/__init__.py
FE_3DGQA/lib/configs/config.py
FE_3DGQA/lib/configs/config_captioning.py
FE_3DGQA/lib/configs/config_grounding.py
FE_3DGQA/lib/configs/config_joint.py
FE_3DGQA/lib/configs/config_vqa.py
FE_3DGQA/lib/joint/__init__.py
FE_3DGQA/lib/joint/dataset.py
FE_3DGQA/lib/joint/eval_caption.py
FE_3DGQA/lib/joint/eval_ground.py
FE_3DGQA/lib/joint/solver_3djcg.py
FE_3DGQA/lib/loss_helper/__init__.py
FE_3DGQA/lib/loss_helper/loss.py
FE_3DGQA/lib/loss_helper/loss_captioning.py
FE_3DGQA/lib/loss_helper/loss_detection.py
FE_3DGQA/lib/loss_helper/loss_grounding.py
FE_3DGQA/lib/loss_helper/loss_grounding_3dvg_trans.py
FE_3DGQA/lib/loss_helper/loss_joint.py
FE_3DGQA/lib/loss_helper/loss_vqa.py
FE_3DGQA/lib/pointnet2/__init__.py
FE_3DGQA/lib/pointnet2/pointnet2_modules.py
FE_3DGQA/lib/pointnet2/pointnet2_utils.py
FE_3DGQA/lib/pointnet2/pytorch_utils.py
FE_3DGQA/lib/pointnet2/setup.py
FE_3DGQA/lib/visual_captioning/__init__.py
FE_3DGQA/lib/visual_captioning/dataset.py
FE_3DGQA/lib/visual_captioning/eval_helper.py
FE_3DGQA/lib/visual_captioning/solver_3djcg_c.py
FE_3DGQA/lib/visual_grounding/__init__.py
FE_3DGQA/lib/visual_grounding/dataset.py
FE_3DGQA/lib/visual_grounding/eval_helper.py
FE_3DGQA/lib/visual_grounding/eval_helper_3dvg_trans.py
FE_3DGQA/lib/visual_grounding/solver_3djcg_g.py
FE_3DGQA/lib/visual_grounding/solver_3dvg_trans.py
FE_3DGQA/lib/visual_question_answering/__init__.py
FE_3DGQA/lib/visual_question_answering/dataset.py
FE_3DGQA-0.1.17.dist-info/METADATA
FE_3DGQA-0.1.17.dist-info/WHEEL
FE_3DGQA-0.1.17.dist-info/top_level.txt
FE_3DGQA-0.1.17.dist-info/RECORD
