Metadata-Version: 2.1
Name: FE-3DGQA
Version: 0.1.17
Summary: FE-3DGQA Model
Home-page: https://github.com/buaacoder/FE-3DGQA
Download-URL: https://github.com/buaacoder/FE-3DGQA/tags
Author: Zhen Wang
Author-email: 1440475233@qq.com
Requires-Python: >=3.7, <3.10
Requires-Dist: torch
Requires-Dist: pillow
Requires-Dist: aiofiles
Requires-Dist: fastapi
Requires-Dist: uvicorn[standard]
Requires-Dist: python-multipart
Requires-Dist: plyfile
Requires-Dist: opencv-python
Requires-Dist: trimesh (==2.35.39)
Requires-Dist: tensorboardX
Requires-Dist: easydict
Requires-Dist: tqdm
Requires-Dist: h5py
Requires-Dist: matplotlib
Requires-Dist: numba
Requires-Dist: transformers
